{
    "name": "All Requests",
    "numberOfRequests": {
        "total": 3500,
        "ok": 3445,
        "ko": 55
    },
    "minResponseTime": {
        "total": 1,
        "ok": 1,
        "ko": 10060
    },
    "maxResponseTime": {
        "total": 10410,
        "ok": 8152,
        "ko": 10410
    },
    "meanResponseTime": {
        "total": 792,
        "ok": 641,
        "ko": 10240
    },
    "standardDeviation": {
        "total": 2183,
        "ok": 1842,
        "ko": 109
    },
    "percentiles1": {
        "total": 4,
        "ok": 4,
        "ko": 10238
    },
    "percentiles2": {
        "total": 11,
        "ok": 9,
        "ko": 10348
    },
    "percentiles3": {
        "total": 7599,
        "ok": 7364,
        "ko": 10400
    },
    "percentiles4": {
        "total": 10184,
        "ok": 7913,
        "ko": 10408
    },
    "group1": {
    "name": "t < 800 ms",
    "htmlName": "t < 800 ms",
    "count": 3000,
    "percentage": 85.71428571428571
},
    "group2": {
    "name": "800 ms <= t < 1200 ms",
    "htmlName": "t >= 800 ms <br> t < 1200 ms",
    "count": 0,
    "percentage": 0.0
},
    "group3": {
    "name": "t >= 1200 ms",
    "htmlName": "t >= 1200 ms",
    "count": 445,
    "percentage": 12.714285714285714
},
    "group4": {
    "name": "failed",
    "htmlName": "failed",
    "count": 55,
    "percentage": 1.5714285714285716
},
    "meanNumberOfRequestsPerSecond": {
        "total": 125.0,
        "ok": 123.03571428571429,
        "ko": 1.9642857142857142
    }
}